openPMD_viewer-1.11.0.data/scripts/openPMD_notebook
openpmd_viewer/__init__.py
openpmd_viewer/__version__.py
openpmd_viewer/addons/__init__.py
openpmd_viewer/addons/pic/__init__.py
openpmd_viewer/addons/pic/lpa_diagnostics.py
openpmd_viewer/notebook_starter/Template_notebook.ipynb
openpmd_viewer/openpmd_timeseries/__init__.py
openpmd_viewer/openpmd_timeseries/data_order.py
openpmd_viewer/openpmd_timeseries/field_metainfo.py
openpmd_viewer/openpmd_timeseries/interactive.py
openpmd_viewer/openpmd_timeseries/main.py
openpmd_viewer/openpmd_timeseries/numba_wrapper.py
openpmd_viewer/openpmd_timeseries/particle_tracker.py
openpmd_viewer/openpmd_timeseries/plotter.py
openpmd_viewer/openpmd_timeseries/utilities.py
openpmd_viewer/openpmd_timeseries/data_reader/__init__.py
openpmd_viewer/openpmd_timeseries/data_reader/data_reader.py
openpmd_viewer/openpmd_timeseries/data_reader/h5py_reader/__init__.py
openpmd_viewer/openpmd_timeseries/data_reader/h5py_reader/field_reader.py
openpmd_viewer/openpmd_timeseries/data_reader/h5py_reader/params_reader.py
openpmd_viewer/openpmd_timeseries/data_reader/h5py_reader/particle_reader.py
openpmd_viewer/openpmd_timeseries/data_reader/h5py_reader/utilities.py
openpmd_viewer/openpmd_timeseries/data_reader/io_reader/__init__.py
openpmd_viewer/openpmd_timeseries/data_reader/io_reader/field_reader.py
openpmd_viewer/openpmd_timeseries/data_reader/io_reader/params_reader.py
openpmd_viewer/openpmd_timeseries/data_reader/io_reader/particle_reader.py
openpmd_viewer/openpmd_timeseries/data_reader/io_reader/utilities.py
opmd_viewer/__init__.py
openPMD_viewer-1.11.0.dist-info/LICENSE.txt
openPMD_viewer-1.11.0.dist-info/METADATA
openPMD_viewer-1.11.0.dist-info/WHEEL
openPMD_viewer-1.11.0.dist-info/top_level.txt
openPMD_viewer-1.11.0.dist-info/RECORD
