Metadata-Version: 2.1
Name: openPMD-viewer
Version: 1.11.0
Summary: Visualization tools for openPMD files
Home-page: https://github.com/openPMD/openPMD-viewer.git
Maintainer: Remi Lehe
Maintainer-email: remi.lehe@lbl.gov
License: BSD-3-Clause-LBNL
Platform: any
Classifier: Programming Language :: Python
Classifier: Development Status :: 4 - Beta
Classifier: Natural Language :: English
Classifier: Environment :: Console
Classifier: Intended Audience :: Science/Research
Classifier: Operating System :: OS Independent
Classifier: Topic :: Scientific/Engineering :: Physics
Classifier: Topic :: Scientific/Engineering :: Visualization
Classifier: Topic :: Database :: Front-Ends
Classifier: Programming Language :: Python :: 3
Classifier: Programming Language :: Python :: 3.8
Classifier: Programming Language :: Python :: 3.9
Classifier: Programming Language :: Python :: 3.10
Classifier: Programming Language :: Python :: 3.11
Requires-Python: >=3.8
License-File: LICENSE.txt
Requires-Dist: numpy >=1.15
Requires-Dist: scipy
Requires-Dist: h5py >=2.8.0
Requires-Dist: tqdm
Provides-Extra: gui
Requires-Dist: ipywidgets ; extra == 'gui'
Requires-Dist: ipympl ; extra == 'gui'
Requires-Dist: matplotlib ; extra == 'gui'
Provides-Extra: all
Requires-Dist: ipympl ; extra == 'all'
Requires-Dist: ipywidgets ; extra == 'all'
Requires-Dist: matplotlib ; extra == 'all'
Requires-Dist: numba ; extra == 'all'
Requires-Dist: openpmd-api ; extra == 'all'
Requires-Dist: wget ; extra == 'all'
Provides-Extra: numba
Requires-Dist: numba ; extra == 'numba'
Provides-Extra: openpmd-api
Requires-Dist: openpmd-api ; extra == 'openpmd-api'
Provides-Extra: plot
Requires-Dist: matplotlib ; extra == 'plot'
Provides-Extra: tutorials
Requires-Dist: ipywidgets ; extra == 'tutorials'
Requires-Dist: ipympl ; extra == 'tutorials'
Requires-Dist: matplotlib ; extra == 'tutorials'
Requires-Dist: wget ; extra == 'tutorials'
